pymnz/__init__.py
pymnz/database/__init__.py
pymnz/database/changes.py
pymnz/database/inspections.py
pymnz/database/updates.py
pymnz/database/upserts.py
pymnz/models/__init__.py
pymnz/models/console.py
pymnz/models/executors.py
pymnz/utils/__init__.py
pymnz/utils/classes.py
pymnz/utils/geometric_calculations.py
pymnz/utils/string.py
pymnz/utils/times.py
pymnz/utils/value_helpers.py
tests/__init__.py
tests/test_imports.py
tests/test_models.py
tests/test_utils.py
pymnz-0.3.8.dist-info/LICENSE
pymnz-0.3.8.dist-info/METADATA
pymnz-0.3.8.dist-info/WHEEL
pymnz-0.3.8.dist-info/top_level.txt
pymnz-0.3.8.dist-info/RECORD
