Metadata-Version: 2.2
Name: pymnz
Version: 0.3.8
Summary: Uma biblioteca para facilitar a criação de scripts de automações com Python
Home-page: https://github.com/mateusflawer/pymnz
Author: Mateus Menezes
Author-email: mateusflawer@gmail.com
Classifier: Programming Language :: Python :: 3
Classifier: License :: OSI Approved :: MIT License
Classifier: Operating System :: OS Independent
Requires-Python: >=3.7
License-File: LICENSE
Dynamic: author
Dynamic: author-email
Dynamic: classifier
Dynamic: description
Dynamic: description-content-type
Dynamic: home-page
Dynamic: requires-python
Dynamic: summary
